README.md
setup.py
version_comparison.egg-info/PKG-INFO
version_comparison.egg-info/SOURCES.txt
version_comparison.egg-info/dependency_links.txt
version_comparison.egg-info/top_level.txt
versions_comparison/__init__.py
versions_comparison/comparison.py
versions_comparison/decorators.py
versions_comparison/exceptions.py