Metadata-Version: 2.1
Name: version-comparison
Version: 0.2
Summary: Get a comparison between 2 version strings
Home-page: https://github.com/estebansolo/david_solorzano_test/tree/master/question_b
Author: Esteban Solorzano
Author-email: estebansolorzano27@gmail.com
License: MIT
Keywords: Compare,Versions
Platform: UNKNOWN
Classifier: Intended Audience :: Developers
Classifier: Topic :: Software Development :: Build Tools
Classifier: License :: OSI Approved :: MIT License
Classifier: Programming Language :: Python :: 3.5
Classifier: Programming Language :: Python :: 3.6
Classifier: Programming Language :: Python :: 3.7
